{
    "ServiceWildcard": [
        "iot"
    ],
    "ServicesAffected": [
        "iot"
    ],
    "PrivilegeEscalation": [],
    "ResourceExposure": [
        "iot:AttachPolicy",
        "iot:AttachPrincipalPolicy",
        "iot:DetachPolicy",
        "iot:DetachPrincipalPolicy",
        "iot:SetDefaultAuthorizer",
        "iot:SetDefaultPolicyVersion"
    ],
    "DataExfiltration": [],
    "CredentialsExposure": [],
    "InfrastructureModification": [
        "iot:AcceptCertificateTransfer",
        "iot:AddThingToBillingGroup",
        "iot:AddThingToThingGroup",
        "iot:AssociateTargetsWithJob",
        "iot:AttachPolicy",
        "iot:AttachPrincipalPolicy",
        "iot:AttachSecurityProfile",
        "iot:CancelCertificateTransfer",
        "iot:CancelJob",
        "iot:CancelJobExecution",
        "iot:CloseTunnel",
        "iot:Connect",
        "iot:CreateAuthorizer",
        "iot:CreateBillingGroup",
        "iot:CreateDimension",
        "iot:CreateDomainConfiguration",
        "iot:CreateDynamicThingGroup",
        "iot:CreateFleetMetric",
        "iot:CreateJob",
        "iot:CreateMitigationAction",
        "iot:CreateOTAUpdate",
        "iot:CreatePolicy",
        "iot:CreatePolicyVersion",
        "iot:CreateProvisioningClaim",
        "iot:CreateProvisioningTemplate",
        "iot:CreateProvisioningTemplateVersion",
        "iot:CreateRoleAlias",
        "iot:CreateScheduledAudit",
        "iot:CreateSecurityProfile",
        "iot:CreateStream",
        "iot:CreateThing",
        "iot:CreateThingGroup",
        "iot:CreateThingType",
        "iot:CreateTopicRule",
        "iot:DeleteAuthorizer",
        "iot:DeleteBillingGroup",
        "iot:DeleteCACertificate",
        "iot:DeleteCertificate",
        "iot:DeleteDimension",
        "iot:DeleteDomainConfiguration",
        "iot:DeleteDynamicThingGroup",
        "iot:DeleteFleetMetric",
        "iot:DeleteJob",
        "iot:DeleteJobExecution",
        "iot:DeleteMitigationAction",
        "iot:DeleteOTAUpdate",
        "iot:DeletePolicy",
        "iot:DeletePolicyVersion",
        "iot:DeleteProvisioningTemplate",
        "iot:DeleteProvisioningTemplateVersion",
        "iot:DeleteRoleAlias",
        "iot:DeleteScheduledAudit",
        "iot:DeleteSecurityProfile",
        "iot:DeleteStream",
        "iot:DeleteThing",
        "iot:DeleteThingGroup",
        "iot:DeleteThingShadow",
        "iot:DeleteThingType",
        "iot:DeleteTopicRule",
        "iot:DeprecateThingType",
        "iot:DetachPolicy",
        "iot:DetachPrincipalPolicy",
        "iot:DetachSecurityProfile",
        "iot:DisableTopicRule",
        "iot:EnableTopicRule",
        "iot:Publish",
        "iot:Receive",
        "iot:RejectCertificateTransfer",
        "iot:RemoveThingFromBillingGroup",
        "iot:RemoveThingFromThingGroup",
        "iot:ReplaceTopicRule",
        "iot:SetDefaultAuthorizer",
        "iot:SetDefaultPolicyVersion",
        "iot:StartNextPendingJobExecution",
        "iot:Subscribe",
        "iot:TagResource",
        "iot:TransferCertificate",
        "iot:UntagResource",
        "iot:UpdateAuthorizer",
        "iot:UpdateBillingGroup",
        "iot:UpdateCACertificate",
        "iot:UpdateCertificate",
        "iot:UpdateDimension",
        "iot:UpdateDomainConfiguration",
        "iot:UpdateDynamicThingGroup",
        "iot:UpdateFleetMetric",
        "iot:UpdateJob",
        "iot:UpdateJobExecution",
        "iot:UpdateMitigationAction",
        "iot:UpdateProvisioningTemplate",
        "iot:UpdateRoleAlias",
        "iot:UpdateScheduledAudit",
        "iot:UpdateSecurityProfile",
        "iot:UpdateStream",
        "iot:UpdateThing",
        "iot:UpdateThingGroup",
        "iot:UpdateThingGroupsForThing",
        "iot:UpdateThingShadow"
    ]
}