{
    "Version": "2012-10-17",
    "Statement": [
        {
            "Effect": "Allow",
            "Action": [
                "route53:*",
                "route53domains:*",
                "cloudfront:ListDistributions",
                "elasticloadbalancing:DescribeLoadBalancers",
                "elasticbeanstalk:DescribeEnvironments",
                "s3:ListBucket",
                "s3:GetBucketLocation",
                "s3:GetBucketWebsiteConfiguration",
                "ec2:DescribeVpcs",
                "ec2:DescribeRegions",
                "sns:ListTopics",
                "sns:ListSubscriptionsByTopic",
                "cloudwatch:DescribeAlarms",
                "cloudwatch:GetMetricStatistics"
            ],
            "Resource": "*"
        }
    ]
}